{
  "parent": "minecraft:husbandry/plant_seed",

  "display": {
    "icon": {
      "item": "flavored:tomato"
    },
    "title": "Fresh fruit!",
    "description": "Obtain your first crops and get cooking!",
    "frame": "task",
    "show_toast": true,
    "announce_to_chat": true
  },
  "criteria": {
    "requirement": {
      "trigger": "minecraft:inventory_changed",
      "conditions": {
        "items": [
          {
              "tag": "flavored:crops"

          }
        ]
      }
    }
  }
}